osm_iterator/__init__.py
osm_iterator/osm_iterator.py
osm_iterator-1.6.0.dist-info/LICENSE
osm_iterator-1.6.0.dist-info/METADATA
osm_iterator-1.6.0.dist-info/WHEEL
osm_iterator-1.6.0.dist-info/top_level.txt
osm_iterator-1.6.0.dist-info/RECORD
