Metadata-Version: 2.2
Name: osm_iterator
Version: 1.6.0
Summary: Iterate over .osm file and call a provided callback function for each element
Home-page: https://github.com/matkoniecz/osm_iterator
Author: Mateusz Konieczny
Author-email: matkoniecz@gmail.com
Classifier: Programming Language :: Python :: 3
Classifier: License :: OSI Approved :: MIT License
Classifier: Operating System :: OS Independent
License-File: LICENSE
Requires-Dist: lxml>=3.5.0
Requires-Dist: nose>=1.3.7
Dynamic: author
Dynamic: author-email
Dynamic: classifier
Dynamic: description
Dynamic: description-content-type
Dynamic: home-page
Dynamic: requires-dist
Dynamic: summary
